{
  "categorias": [
    { "id": "todos", "nombre": "Tutti", "icono": "fas fa-ice-cream" },
    { "id": "clasicos", "nombre": "Classici", "icono": "fas fa-star" },
    { "id": "sorbetes", "nombre": "Sorbetti", "icono": "fas fa-snowflake" },
    { "id": "especiales", "nombre": "Speciali", "icono": "fas fa-gem" }
  ],
  "helados": [
    { "id": 1, "nombre": "Vainilla", "descripcion": "Autentica vaniglia bourbon con semi naturali visibili", "imagen": "assets/img/lotus.jpeg", "categoria": "clasicos", "badgeTexto": "Classico", "badgeClase": "clasico", "alergenos": [{ "tipo": "lacteos", "titulo": "Contiene latticini", "icono": "fas fa-cow", "clase": "" }] },
    { "id": 2, "nombre": "Fresa", "descripcion": "Fragole fresche di stagione con base cremosa di panna", "imagen": "assets/img/lotus.jpeg", "categoria": "clasicos", "badgeTexto": "Classico", "badgeClase": "clasico", "alergenos": [{ "tipo": "lacteos", "titulo": "Contiene latticini", "icono": "fas fa-cow", "clase": "" }] },
    { "id": 3, "nombre": "Pistacho", "descripcion": "Autentico pistacchio, colore verde naturale intenso", "imagen": "assets/img/lotus.jpeg", "categoria": "clasicos", "badgeTexto": "Classico", "badgeClase": "clasico", "alergenos": [{ "tipo": "lacteos", "titulo": "Contiene latticini", "icono": "fas fa-cow", "clase": "" }, { "tipo": "frutos_secos", "titulo": "Contiene frutta secca (pistacchio)", "icono": "fas fa-circle-exclamation", "clase": "" }] },
    { "id": 4, "nombre": "Chocolate Leche", "descripcion": "Delicato cioccolato al latte, cremoso e raffinato", "imagen": "assets/img/lotus.jpeg", "categoria": "clasicos", "badgeTexto": "Classico", "badgeClase": "clasico", "alergenos": [{ "tipo": "lacteos", "titulo": "Contiene latticini", "icono": "fas fa-cow", "clase": "" }] },
    { "id": 5, "nombre": "Café", "descripcion": "Intenso caffè espresso italiano con un tocco cremoso", "imagen": "assets/img/lotus.jpeg", "categoria": "clasicos", "badgeTexto": "Classico", "badgeClase": "clasico", "alergenos": [{ "tipo": "lacteos", "titulo": "Contiene latticini", "icono": "fas fa-cow", "clase": "" }] },
    { "id": 6, "nombre": "Turrón", "descripcion": "Tradizionale torrone spagnolo", "imagen": "assets/img/lotus.jpeg", "categoria": "clasicos", "badgeTexto": "Classico", "badgeClase": "clasico", "alergenos": [{ "tipo": "lacteos", "titulo": "Contiene latticini", "icono": "fas fa-cow", "clase": "" }, { "tipo": "huevo", "titulo": "Contiene uova", "icono": "fas fa-egg", "clase": "" }, { "tipo": "frutos_secos", "titulo": "Contiene frutta secca (mandorla)", "icono": "fas fa-circle-exclamation", "clase": "" }] },
    { "id": 7, "nombre": "Limón Siciliano", "descripcion": "Sorbetto rinfrescante di limoni siciliani, 100% naturale", "imagen": "assets/img/lotus.jpeg", "categoria": "sorbetes", "badgeTexto": "Sorbetto", "badgeClase": "sorbete", "alergenos": [{ "tipo": "vegano", "titulo": "Vegano", "icono": "fas fa-leaf", "clase": "vegano" }] },
    { "id": 8, "nombre": "Mango", "descripcion": "Mango fresco tropicale con un tocco di lime naturale", "imagen": "assets/img/lotus.jpeg", "categoria": "sorbetes", "badgeTexto": "Sorbetto", "badgeClase": "sorbete", "alergenos": [{ "tipo": "vegano", "titulo": "Vegano", "icono": "fas fa-leaf", "clase": "vegano" }] },
    { "id": 9, "nombre": "Dark", "descripcion": "Intenso cioccolato fondente 85% cacao, senza latticini", "imagen": "assets/img/lotus.jpeg", "categoria": "sorbetes", "badgeTexto": "Sorbetto", "badgeClase": "sorbete", "alergenos": [{ "tipo": "vegano", "titulo": "Vegano", "icono": "fas fa-leaf", "clase": "vegano" }] },
    { "id": 10, "nombre": "Frutas del Bosque", "descripcion": "Miscela di lamponi, more e mirtilli freschi", "imagen": "assets/img/lotus.jpeg", "categoria": "sorbetes", "badgeTexto": "Sorbetto", "badgeClase": "sorbete", "alergenos": [{ "tipo": "vegano", "titulo": "Vegano", "icono": "fas fa-leaf", "clase": "vegano" }] },
    { "id": 11, "nombre": "Nube", "descripcion": "Gelato morbido e spumoso con texture a nuvola", "imagen": "assets/img/lotus.jpeg", "categoria": "especiales", "badgeTexto": "Speciale", "badgeClase": "especial", "alergenos": [{ "tipo": "lacteos", "titulo": "Contiene latticini", "icono": "fas fa-cow", "clase": "" }] },
    { "id": 12, "nombre": "MentaChoco", "descripcion": "Menta naturale rinfrescante con scaglie di cioccolato", "imagen": "assets/img/lotus.jpeg", "categoria": "especiales", "badgeTexto": "Speciale", "badgeClase": "especial", "alergenos": [{ "tipo": "lacteos", "titulo": "Contiene latticini", "icono": "fas fa-cow", "clase": "" }] },
    { "id": 13, "nombre": "Oreo", "descripcion": "Gelato cremoso con pezzi di biscotti Oreo originali", "imagen": "assets/img/lotus.jpeg", "categoria": "especiales", "badgeTexto": "Speciale", "badgeClase": "especial", "alergenos": [{ "tipo": "lacteos", "titulo": "Contiene latticini", "icono": "fas fa-cow", "clase": "" }, { "tipo": "gluten", "titulo": "Contiene glutine (biscotto)", "icono": "fas fa-wheat-awn", "clase": "" }] },
    { "id": 14, "nombre": "Stracciatella", "descripcion": "Panna con scaglie di cioccolato fondente in stile italiano", "imagen": "assets/img/lotus.jpeg", "categoria": "especiales", "badgeTexto": "Speciale", "badgeClase": "especial", "alergenos": [{ "tipo": "lacteos", "titulo": "Contiene latticini", "icono": "fas fa-cow", "clase": "" }] },
    { "id": 15, "nombre": "Kinder", "descripcion": "Ispirato al Kinder Bueno, con biscotto e nocciole", "imagen": "assets/img/kinder.jpeg", "categoria": "especiales", "badgeTexto": "Speciale", "badgeClase": "especial", "alergenos": [{ "tipo": "lacteos", "titulo": "Contiene latticini", "icono": "fas fa-cow", "clase": "" }, { "tipo": "gluten", "titulo": "Contiene glutine (biscotto)", "icono": "fas fa-wheat-awn", "clase": "" }, { "tipo": "frutos_secos", "titulo": "Contiene frutta secca (nocciola)", "icono": "fas fa-circle-exclamation", "clase": "" }] },
    { "id": 16, "nombre": "Lotus", "descripcion": "Gelato cremoso con pezzi di biscotti Lotus caramellati", "imagen": "assets/img/lotus.jpeg", "categoria": "especiales", "badgeTexto": "Speciale", "badgeClase": "especial", "alergenos": [{ "tipo": "lacteos", "titulo": "Contiene latticini", "icono": "fas fa-cow", "clase": "" }, { "tipo": "gluten", "titulo": "Contiene glutine (biscotto)", "icono": "fas fa-wheat-awn", "clase": "" }] },
    { "id": 17, "nombre": "Yogurt Amarena", "descripcion": "Yogurt naturale con ciliegie amarena italiane", "imagen": "assets/img/lotus.jpeg", "categoria": "especiales", "badgeTexto": "Speciale", "badgeClase": "especial", "alergenos": [{ "tipo": "lacteos", "titulo": "Contiene latticini", "icono": "fas fa-cow", "clase": "" }] },
    { "id": 18, "nombre": "Carapino", "descripcion": "Delizioso caramello tostato con pinoli croccanti", "imagen": "assets/img/lotus.jpeg", "categoria": "especiales", "badgeTexto": "Speciale", "badgeClase": "especial", "alergenos": [{ "tipo": "lacteos", "titulo": "Contiene latticini", "icono": "fas fa-cow", "clase": "" }, { "tipo": "frutos_secos", "titulo": "Contiene frutta secca (pinoli)", "icono": "fas fa-circle-exclamation", "clase": "" }] },
    { "id": 19, "nombre": "Málaga", "descripcion": "Tradizionale gelato con uvetta al rum, stile malagueño", "imagen": "assets/img/lotus.jpeg", "categoria": "especiales", "badgeTexto": "Speciale", "badgeClase": "especial", "alergenos": [{ "tipo": "lacteos", "titulo": "Contiene latticini", "icono": "fas fa-cow", "clase": "" }, { "tipo": "alcohol", "titulo": "Contiene alcol", "icono": "fas fa-wine-bottle", "clase": "" }] },
    { "id": 20, "nombre": "Tarta de Queso", "descripcion": "Cremosa cheesecake con base di biscotto", "imagen": "assets/img/lotus.jpeg", "categoria": "especiales", "badgeTexto": "Speciale", "badgeClase": "especial", "alergenos": [{ "tipo": "lacteos", "titulo": "Contiene latticini", "icono": "fas fa-cow", "clase": "" }, { "tipo": "gluten", "titulo": "Contiene glutine (biscotto)", "icono": "fas fa-wheat-awn", "clase": "" }] },
    { "id": 21, "nombre": "Mascarpone con Dulce de Leche", "descripcion": "Morbido e cremoso formaggio mascarpone italiano con dulce de leche", "imagen": "assets/img/lotus.jpeg", "categoria": "especiales", "badgeTexto": "Speciale", "badgeClase": "especial", "alergenos": [{ "tipo": "lacteos", "titulo": "Contiene latticini", "icono": "fas fa-cow", "clase": "" }] },
    { "id": 22, "nombre": "Happy Hippo", "descripcion": "Ispirato all'Happy Hippo, con nocciole e biscotto croccante", "imagen": "assets/img/lotus.jpeg", "categoria": "especiales", "badgeTexto": "Speciale", "badgeClase": "especial", "alergenos": [{ "tipo": "lacteos", "titulo": "Contiene latticini", "icono": "fas fa-cow", "clase": "" }, { "tipo": "gluten", "titulo": "Contiene glutine (biscotto)", "icono": "fas fa-wheat-awn", "clase": "" }, { "tipo": "frutos_secos", "titulo": "Contiene frutta secca (nocciola)", "icono": "fas fa-circle-exclamation", "clase": "" }] },
    { "id": 23, "nombre": "Raffaello", "descripcion": "Squisito cocco cremoso ispirato ai cioccolatini Raffaello", "imagen": "assets/img/lotus.jpeg", "categoria": "especiales", "badgeTexto": "Speciale", "badgeClase": "especial", "alergenos": [{ "tipo": "lacteos", "titulo": "Contiene latticini", "icono": "fas fa-cow", "clase": "" }] }
  ],
  "alergenosInfo": [
    { "icono": "fas fa-cow", "nombre": "Latticini", "descripcion": "Contiene latte o prodotti lattiero-caseari" },
    { "icono": "fas fa-egg", "nombre": "Uova", "descripcion": "Contiene uova o derivati" },
    { "icono": "fas fa-circle-exclamation", "nombre": "Frutta Secca", "descripcion": "Contiene mandorle, nocciole, pistacchi, pinoli, ecc." },
    { "icono": "fas fa-wheat-awn", "nombre": "Glutine", "descripcion": "Contiene frumento, orzo o glutine" },
    { "icono": "fas fa-leaf", "nombre": "Vegano", "descripcion": "100% vegetale, senza ingredienti animali" },
    { "icono": "fas fa-wine-bottle", "nombre": "Alcol", "descripcion": "Contiene alcol" }
  ],
  "notaImportante": "Tutti i nostri gelati vengono elaborati nello stesso spazio, pertanto può esserci contaminazione crociata. Se hai allergie severe, consulta il nostro personale prima di effettuare il tuo ordine."
}
